[{"playerName":"Pat Cummins","over":"4","madenOver":"0","runs":"17","wicket":"3","Econ":"4.25","zeros":"16","fours":"3","sixes":"0","wide":"0","noBall":"0"},{"playerName":"Prasidh Krishna","over":"2","madenOver":"0","runs":"19","wicket":"0","Econ":"9.50","zeros":"4","fours":"1","sixes":"1","wide":"1","noBall":"2"},{"playerName":"Kamlesh Nagarkoti","over":"2","madenOver":"0","runs":"11","wicket":"0","Econ":"5.50","zeros":"7","fours":"2","sixes":"0","wide":"0","noBall":"0"},{"playerName":"Lockie Ferguson","over":"4","madenOver":"0","runs":"30","wicket":"1","Econ":"7.50","zeros":"8","fours":"4","sixes":"0","wide":"0","noBall":"0"},{"playerName":"Sunil Narine","over":"4","madenOver":"0","runs":"37","wicket":"0","Econ":"9.25","zeros":"4","fours":"0","sixes":"2","wide":"1","noBall":"0"},{"playerName":"Varun Chakravarthy","over":"4","madenOver":"0","runs":"20","wicket":"5","Econ":"5.00","zeros":"9","fours":"1","sixes":"0","wide":"1","noBall":"0"}]